llmzoo/__init__.py
llmzoo/factory.py
llmzoo/core/base.py
llmzoo/providers/__init__.py
llmzoo/providers/bedrock.py
llmzoo/providers/moonshot.py
llmzoo/providers/openai_compat.py
llmzoo/providers/zhipu.py
llmzoo/vectorstores/__init__.py
llmzoo/vectorstores/chroma.py
llmzoo/vectorstores/elasticsearch.py
llmzoo/vectorstores/milvus_lite.py
llmzoo/vectorstores/opensearch.py
llmzoo/vectorstores/pgvector.py
llmzoo-0.1.1.dist-info/METADATA
llmzoo-0.1.1.dist-info/WHEEL
llmzoo-0.1.1.dist-info/top_level.txt
llmzoo-0.1.1.dist-info/RECORD
