Metadata-Version: 2.4
Name: llmzoo
Version: 0.1.1
Summary: Lightweight, extensible LLM toolkit: chat, embeddings, vector stores (Chroma, Milvus Lite).
Author: llmpy authors
License: MIT
Project-URL: Homepage, https://github.com/yourusername/llmpy
Project-URL: Repository, https://github.com/yourusername/llmpy
Project-URL: Issues, https://github.com/yourusername/llmpy/issues
Keywords: LLM,RAG,embeddings,chat,vectorstore,chroma,milvus
Requires-Python: >=3.9
Requires-Dist: requests>=2.31.0
Requires-Dist: typing-extensions>=4.8.0
Provides-Extra: chroma
Requires-Dist: chromadb>=0.5.0; extra == "chroma"
Provides-Extra: milvus
Requires-Dist: pymilvus>=2.4.0; extra == "milvus"
Provides-Extra: pg
Requires-Dist: psycopg[binary]>=3.2.1; extra == "pg"
Requires-Dist: pgvector>=0.3.3; extra == "pg"
Provides-Extra: es
Requires-Dist: elasticsearch>=8.13.0; extra == "es"
Provides-Extra: opensearch
Requires-Dist: opensearch-py>=2.5.0; extra == "opensearch"
Provides-Extra: dev
Requires-Dist: pytest>=7.4.0; extra == "dev"
Requires-Dist: ruff>=0.5.0; extra == "dev"
